pref_vote/STV.py
pref_vote/__init__.py
pref_vote/poll.py
pref_vote-0.0.7.dist-info/DESCRIPTION.rst
pref_vote-0.0.7.dist-info/METADATA
pref_vote-0.0.7.dist-info/RECORD
pref_vote-0.0.7.dist-info/WHEEL
pref_vote-0.0.7.dist-info/metadata.json
pref_vote-0.0.7.dist-info/top_level.txt
