Metadata-Version: 2.0
Name: pref-vote
Version: 0.0.7
Summary: Preferential voting tool
Home-page: https://github.com/jmhossler/pref_vote
Author: John Hossler
Author-email: john.m.hossler@gmail.com
License: none
Platform: UNKNOWN
Classifier: Development Status :: 4 - Beta
Classifier: Programming Language :: Python
